graphql_printers/__init__.py
graphql_printers/backends.py
graphql_printers/compact_printing_visitor.py
graphql_printers/filtering_visitor.py
graphql_core_printers-0.0.1.dist-info/METADATA
graphql_core_printers-0.0.1.dist-info/WHEEL
graphql_core_printers-0.0.1.dist-info/top_level.txt
graphql_core_printers-0.0.1.dist-info/RECORD
