Metadata-Version: 2.1
Name: graphql-core-printers
Version: 0.0.1
Summary: Print GraphQL queries while masking secrets. Useful for logging with graphql-core.
Home-page: https://github.com/ktosiek/graphql-core-printers
Author: Tomasz Kontusz
Author-email: tomasz.kontusz@gmail.com
Maintainer: Tomasz Kontusz
Maintainer-email: tomasz.kontusz@gmail.com
License: MIT
Platform: UNKNOWN
Classifier: Programming Language :: Python :: 3
Classifier: Operating System :: OS Independent
Classifier: License :: OSI Approved :: MIT License
Requires-Dist: graphql-core (<3,>=2.1)
Provides-Extra: test
Requires-Dist: pytest ; extra == 'test'
Requires-Dist: pytest-benchmark ; extra == 'test'
Requires-Dist: snapshottest ; extra == 'test'
Requires-Dist: wheel ; extra == 'test'
